sentieoslack/__init__.py
sentieoslack/constants.py
sentieoslack/py.typed
sentieoslack/service.py
sentieoslack/utility.py
sentieoslack-0.0.1.dist-info/METADATA
sentieoslack-0.0.1.dist-info/WHEEL
sentieoslack-0.0.1.dist-info/entry_points.txt
sentieoslack-0.0.1.dist-info/RECORD
