Metadata-Version: 2.1
Name: sentieoslack
Version: 0.0.1
Summary: Sentieoslack
Author: shivangi-mittal-sentieo
Author-email: shivangi.mittal@sentieo.com
Requires-Python: >=3.8,<4.0
Classifier: Programming Language :: Python :: 3
Classifier: Programming Language :: Python :: 3.8
Classifier: Programming Language :: Python :: 3.9
Classifier: Programming Language :: Python :: 3.10
Classifier: Programming Language :: Python :: 3.11
Classifier: Programming Language :: Python :: 3.12
Requires-Dist: slack-sdk (>=3.17.0,<4.0.0)
